{"data_mtime": 1685697826, "dep_lines": [25, 15, 16, 17, 27, 32, 33, 36, 37, 39, 2, 3, 4, 5, 6, 7, 8, 20, 209, 1, 1, 1, 1, 1, 1, 1, 1, 1, 1, 1, 1], "dep_prios": [5, 5, 5, 5, 5, 5, 5, 5, 5, 5, 10, 10, 10, 10, 5, 5, 5, 25, 20, 5, 30, 30, 30, 30, 30, 30, 30, 30, 30, 30, 30], "dependencies": ["_pytest.config.argparsing", "_pytest.nodes", "_pytest.reports", "_pytest.stash", "_pytest.pathlib", "_pytest.compat", "_pytest.config", "_pytest.deprecated", "_pytest.fixtures", "_pytest.monkeypatch", "dataclasses", "os", "re", "tempfile", "pathlib", "shutil", "typing", "typing_extensions", "getpass", "builtins", "_pytest.hookspec", "_pytest.main", "_pytest.mark", "_typeshed", "abc", "argparse", "array", "ctypes", "enum", "mmap", "pickle"], "hash": "9b47e7ba4640ec5aea6243dc5c4baddabdcff5447ce8f147d2d1cae188419160", "id": "_pytest.tmpdir", "ignore_all": true, "interface_hash": "04e0f57cbe0183ba8cd7cf291ba7fbefe44aa5889b80382d3977b51a5108fe30", "mtime": 1681495843, "options": {"allow_redefinition": true, "allow_untyped_globals": false, "always_false": [], "always_true": [], "bazel": false, "check_untyped_defs": false, "disable_bytearray_promotion": false, "disable_error_code": [], "disable_memoryview_promotion": false, "disabled_error_codes": [], "disallow_any_decorated": false, "disallow_any_explicit": false, "disallow_any_expr": false, "disallow_any_generics": false, "disallow_any_unimported": false, "disallow_incomplete_defs": false, "disallow_subclassing_any": false, "disallow_untyped_calls": false, "disallow_untyped_decorators": false, "disallow_untyped_defs": false, "enable_error_code": [], "enabled_error_codes": [], "follow_imports": "silent", "follow_imports_for_stubs": false, "ignore_errors": false, "ignore_missing_imports": true, "implicit_optional": false, "implicit_reexport": true, "local_partial_types": false, "mypyc": false, "platform": "linux", "plugins": [], "strict_concatenate": false, "strict_equality": false, "strict_optional": true, "warn_no_return": true, "warn_return_any": false, "warn_unreachable": false, "warn_unused_ignores": false}, "path": "/home/anton/micromamba/envs/py310/lib/python3.10/site-packages/_pytest/tmpdir.py", "plugin_data": null, "size": 11709, "suppressed": [], "version_id": "1.1.1"}