{".class": "MypyFile", "_fullname": "sphinx.domains.math", "future_import_flags": [], "is_partial_stub_package": false, "is_stub": false, "names": {".class": "SymbolTable", "Any": {".class": "SymbolTableNode", "cross_ref": "typing.Any", "kind": "Gdef"}, "BuildEnvironment": {".class": "SymbolTableNode", "cross_ref": "sphinx.environment.BuildEnvironment", "kind": "Gdef"}, "Builder": {".class": "SymbolTableNode", "cross_ref": "sphinx.builders.Builder", "kind": "Gdef"}, "Dict": {".class": "SymbolTableNode", "cross_ref": "typing.Dict", "kind": "Gdef"}, "Domain": {".class": "SymbolTableNode", "cross_ref": "sphinx.domains.Domain", "kind": "Gdef"}, "Element": {".class": "SymbolTableNode", "kind": "Gdef", "node": {".class": "Var", "flags": ["is_suppressed_import", "is_ready", "is_inferred"], "fullname": "sphinx.domains.math.Element", "name": "Element", "type": {".class": "AnyType", "missing_import_name": "sphinx.domains.math.Element", "source_any": null, "type_of_any": 3}}}, "Iterable": {".class": "SymbolTableNode", "cross_ref": "typing.Iterable", "kind": "Gdef"}, "List": {".class": "SymbolTableNode", "cross_ref": "typing.List", "kind": "Gdef"}, "MathDomain": {".class": "SymbolTableNode", "kind": "Gdef", "node": {".class": "TypeInfo", "_promote": [], "abstract_attributes": [], "alt_promote": null, "bases": ["sphinx.domains.Domain"], "dataclass_transform_spec": null, "declared_metaclass": null, "defn": {".class": "ClassDef", "fullname": "sphinx.domains.math.MathDomain", "name": "MathDomain", "type_vars": []}, "deletable_attributes": [], "flags": [], "fullname": "sphinx.domains.math.MathDomain", "has_param_spec_type": false, "metaclass_type": null, "metadata": {}, "module_name": "sphinx.domains.math", "mro": ["sphinx.domains.math.MathDomain", "sphinx.domains.Domain", "builtins.object"], "names": {".class": "SymbolTable", "clear_doc": {".class": "SymbolTableNode", "kind": "Mdef", "node": {".class": "FuncDef", "abstract_status": 0, "arg_kinds": [0, 0], "arg_names": ["self", "docname"], "dataclass_transform_spec": null, "flags": [], "fullname": "sphinx.domains.math.MathDomain.clear_doc", "name": "clear_doc", "type": {".class": "CallableType", "arg_kinds": [0, 0], "arg_names": ["self", "docname"], "arg_types": ["sphinx.domains.math.MathDomain", "builtins.str"], "bound_args": [], "def_extras": {"first_arg": "self"}, "fallback": "builtins.function", "from_concatenate": false, "implicit": false, "is_ellipsis_args": false, "name": "clear_doc of MathDomain", "ret_type": {".class": "NoneType"}, "type_guard": null, "unpack_kwargs": false, "variables": []}}}, "dangling_warnings": {".class": "SymbolTableNode", "kind": "Mdef", "node": {".class": "Var", "flags": ["is_initialized_in_class", "is_inferred", "has_explicit_value"], "fullname": "sphinx.domains.math.MathDomain.dangling_warnings", "name": "dangling_warnings", "type": {".class": "Instance", "args": ["builtins.str", "builtins.str"], "type_ref": "builtins.dict"}}}, "enumerable_nodes": {".class": "SymbolTableNode", "kind": "Mdef", "node": {".class": "Var", "flags": ["is_initialized_in_class", "is_inferred", "has_explicit_value"], "fullname": "sphinx.domains.math.MathDomain.enumerable_nodes", "name": "enumerable_nodes", "type": {".class": "Instance", "args": [{".class": "TypeType", "item": {".class": "AnyType", "missing_import_name": "sphinx.domains.Node", "source_any": null, "type_of_any": 3}}, {".class": "TupleType", "implicit": false, "items": ["builtins.str", {".class": "CallableType", "arg_kinds": [2, 4], "arg_names": [null, null], "arg_types": [{".class": "AnyType", "missing_import_name": null, "source_any": null, "type_of_any": 4}, {".class": "AnyType", "missing_import_name": null, "source_any": null, "type_of_any": 4}], "bound_args": [], "def_extras": {}, "fallback": "builtins.function", "from_concatenate": false, "implicit": false, "is_ellipsis_args": true, "name": null, "ret_type": {".class": "AnyType", "missing_import_name": null, "source_any": null, "type_of_any": 4}, "type_guard": null, "unpack_kwargs": false, "variables": []}], "partial_fallback": {".class": "Instance", "args": [{".class": "AnyType", "missing_import_name": null, "source_any": null, "type_of_any": 6}], "type_ref": "builtins.tuple"}}], "type_ref": "builtins.dict"}}}, "equations": {".class": "SymbolTableNode", "kind": "Mdef", "node": {".class": "Decorator", "func": {".class": "FuncDef", "abstract_status": 0, "arg_kinds": [0], "arg_names": ["self"], "dataclass_transform_spec": null, "flags": ["is_property", "is_decorated"], "fullname": "sphinx.domains.math.MathDomain.equations", "name": "equations", "type": {".class": "CallableType", "arg_kinds": [0], "arg_names": ["self"], "arg_types": ["sphinx.domains.math.MathDomain"], "bound_args": [], "def_extras": {"first_arg": "self"}, "fallback": "builtins.function", "from_concatenate": false, "implicit": false, "is_ellipsis_args": false, "name": "equations of MathDomain", "ret_type": {".class": "Instance", "args": ["builtins.str", {".class": "TupleType", "implicit": false, "items": ["builtins.str", "builtins.int"], "partial_fallback": {".class": "Instance", "args": [{".class": "AnyType", "missing_import_name": null, "source_any": null, "type_of_any": 6}], "type_ref": "builtins.tuple"}}], "type_ref": "builtins.dict"}, "type_guard": null, "unpack_kwargs": false, "variables": []}}, "is_overload": false, "var": {".class": "Var", "flags": ["is_initialized_in_class", "is_property", "is_ready", "is_inferred"], "fullname": "sphinx.domains.math.MathDomain.equations", "name": "equations", "type": {".class": "CallableType", "arg_kinds": [0], "arg_names": ["self"], "arg_types": ["sphinx.domains.math.MathDomain"], "bound_args": [], "def_extras": {"first_arg": "self"}, "fallback": "builtins.function", "from_concatenate": false, "implicit": false, "is_ellipsis_args": false, "name": "equations of MathDomain", "ret_type": {".class": "Instance", "args": ["builtins.str", {".class": "TupleType", "implicit": false, "items": ["builtins.str", "builtins.int"], "partial_fallback": {".class": "Instance", "args": [{".class": "AnyType", "missing_import_name": null, "source_any": null, "type_of_any": 6}], "type_ref": "builtins.tuple"}}], "type_ref": "builtins.dict"}, "type_guard": null, "unpack_kwargs": false, "variables": []}}}}, "get_equation_number_for": {".class": "SymbolTableNode", "kind": "Mdef", "node": {".class": "FuncDef", "abstract_status": 0, "arg_kinds": [0, 0], "arg_names": ["self", "labelid"], "dataclass_transform_spec": null, "flags": [], "fullname": "sphinx.domains.math.MathDomain.get_equation_number_for", "name": "get_equation_number_for", "type": {".class": "CallableType", "arg_kinds": [0, 0], "arg_names": ["self", "labelid"], "arg_types": ["sphinx.domains.math.MathDomain", "builtins.str"], "bound_args": [], "def_extras": {"first_arg": "self"}, "fallback": "builtins.function", "from_concatenate": false, "implicit": false, "is_ellipsis_args": false, "name": "get_equation_number_for of MathDomain", "ret_type": "builtins.int", "type_guard": null, "unpack_kwargs": false, "variables": []}}}, "get_objects": {".class": "SymbolTableNode", "kind": "Mdef", "node": {".class": "FuncDef", "abstract_status": 0, "arg_kinds": [0], "arg_names": ["self"], "dataclass_transform_spec": null, "flags": [], "fullname": "sphinx.domains.math.MathDomain.get_objects", "name": "get_objects", "type": {".class": "CallableType", "arg_kinds": [0], "arg_names": ["self"], "arg_types": ["sphinx.domains.math.MathDomain"], "bound_args": [], "def_extras": {"first_arg": "self"}, "fallback": "builtins.function", "from_concatenate": false, "implicit": false, "is_ellipsis_args": false, "name": "get_objects of MathDomain", "ret_type": {".class": "Instance", "args": [{".class": "AnyType", "missing_import_name": null, "source_any": null, "type_of_any": 4}], "type_ref": "builtins.list"}, "type_guard": null, "unpack_kwargs": false, "variables": []}}}, "has_equations": {".class": "SymbolTableNode", "kind": "Mdef", "node": {".class": "FuncDef", "abstract_status": 0, "arg_kinds": [0, 1], "arg_names": ["self", "docname"], "dataclass_transform_spec": null, "flags": [], "fullname": "sphinx.domains.math.MathDomain.has_equations", "name": "has_equations", "type": {".class": "CallableType", "arg_kinds": [0, 1], "arg_names": ["self", "docname"], "arg_types": ["sphinx.domains.math.MathDomain", "builtins.str"], "bound_args": [], "def_extras": {"first_arg": "self"}, "fallback": "builtins.function", "from_concatenate": false, "implicit": false, "is_ellipsis_args": false, "name": "has_equations of MathDomain", "ret_type": "builtins.bool", "type_guard": null, "unpack_kwargs": false, "variables": []}}}, "initial_data": {".class": "SymbolTableNode", "kind": "Mdef", "node": {".class": "Var", "flags": ["is_initialized_in_class", "is_ready", "has_explicit_value"], "fullname": "sphinx.domains.math.MathDomain.initial_data", "name": "initial_data", "type": {".class": "Instance", "args": [{".class": "AnyType", "missing_import_name": null, "source_any": null, "type_of_any": 4}, {".class": "AnyType", "missing_import_name": null, "source_any": null, "type_of_any": 4}], "type_ref": "builtins.dict"}}}, "label": {".class": "SymbolTableNode", "kind": "Mdef", "node": {".class": "Var", "flags": ["is_initialized_in_class", "is_inferred", "has_explicit_value"], "fullname": "sphinx.domains.math.MathDomain.label", "name": "label", "type": "builtins.str"}}, "merge_domaindata": {".class": "SymbolTableNode", "kind": "Mdef", "node": {".class": "FuncDef", "abstract_status": 0, "arg_kinds": [0, 0, 0], "arg_names": ["self", "docnames", "otherdata"], "dataclass_transform_spec": null, "flags": [], "fullname": "sphinx.domains.math.MathDomain.merge_domaindata", "name": "merge_domaindata", "type": {".class": "CallableType", "arg_kinds": [0, 0, 0], "arg_names": ["self", "docnames", "otherdata"], "arg_types": ["sphinx.domains.math.MathDomain", {".class": "Instance", "args": ["builtins.str"], "type_ref": "typing.Iterable"}, {".class": "Instance", "args": [{".class": "AnyType", "missing_import_name": null, "source_any": null, "type_of_any": 4}, {".class": "AnyType", "missing_import_name": null, "source_any": null, "type_of_any": 4}], "type_ref": "builtins.dict"}], "bound_args": [], "def_extras": {"first_arg": "self"}, "fallback": "builtins.function", "from_concatenate": false, "implicit": false, "is_ellipsis_args": false, "name": "merge_domaindata of MathDomain", "ret_type": {".class": "NoneType"}, "type_guard": null, "unpack_kwargs": false, "variables": []}}}, "name": {".class": "SymbolTableNode", "kind": "Mdef", "node": {".class": "Var", "flags": ["is_initialized_in_class", "is_inferred", "has_explicit_value"], "fullname": "sphinx.domains.math.MathDomain.name", "name": "name", "type": "builtins.str"}}, "note_equation": {".class": "SymbolTableNode", "kind": "Mdef", "node": {".class": "FuncDef", "abstract_status": 0, "arg_kinds": [0, 0, 0, 1], "arg_names": ["self", "docname", "labelid", "location"], "dataclass_transform_spec": null, "flags": [], "fullname": "sphinx.domains.math.MathDomain.note_equation", "name": "note_equation", "type": {".class": "CallableType", "arg_kinds": [0, 0, 0, 1], "arg_names": ["self", "docname", "labelid", "location"], "arg_types": ["sphinx.domains.math.MathDomain", "builtins.str", "builtins.str", {".class": "AnyType", "missing_import_name": null, "source_any": null, "type_of_any": 2}], "bound_args": [], "def_extras": {"first_arg": "self"}, "fallback": "builtins.function", "from_concatenate": false, "implicit": false, "is_ellipsis_args": false, "name": "note_equation of MathDomain", "ret_type": {".class": "NoneType"}, "type_guard": null, "unpack_kwargs": false, "variables": []}}}, "process_doc": {".class": "SymbolTableNode", "kind": "Mdef", "node": {".class": "FuncDef", "abstract_status": 0, "arg_kinds": [0, 0, 0, 0], "arg_names": ["self", "env", "docname", "document"], "dataclass_transform_spec": null, "flags": [], "fullname": "sphinx.domains.math.MathDomain.process_doc", "name": "process_doc", "type": {".class": "CallableType", "arg_kinds": [0, 0, 0, 0], "arg_names": ["self", "env", "docname", "document"], "arg_types": ["sphinx.domains.math.MathDomain", "sphinx.environment.BuildEnvironment", "builtins.str", {".class": "AnyType", "missing_import_name": "sphinx.domains.math.nodes", "source_any": null, "type_of_any": 3}], "bound_args": [], "def_extras": {"first_arg": "self"}, "fallback": "builtins.function", "from_concatenate": false, "implicit": false, "is_ellipsis_args": false, "name": "process_doc of MathDomain", "ret_type": {".class": "NoneType"}, "type_guard": null, "unpack_kwargs": false, "variables": []}}}, "resolve_any_xref": {".class": "SymbolTableNode", "kind": "Mdef", "node": {".class": "FuncDef", "abstract_status": 0, "arg_kinds": [0, 0, 0, 0, 0, 0, 0], "arg_names": ["self", "env", "fromdocname", "builder", "target", "node", "contnode"], "dataclass_transform_spec": null, "flags": [], "fullname": "sphinx.domains.math.MathDomain.resolve_any_xref", "name": "resolve_any_xref", "type": {".class": "CallableType", "arg_kinds": [0, 0, 0, 0, 0, 0, 0], "arg_names": ["self", "env", "fromdocname", "builder", "target", "node", "contnode"], "arg_types": ["sphinx.domains.math.MathDomain", "sphinx.environment.BuildEnvironment", "builtins.str", "sphinx.builders.Builder", "builtins.str", "sphinx.addnodes.pending_xref", {".class": "AnyType", "missing_import_name": "sphinx.domains.math.Element", "source_any": null, "type_of_any": 3}], "bound_args": [], "def_extras": {"first_arg": "self"}, "fallback": "builtins.function", "from_concatenate": false, "implicit": false, "is_ellipsis_args": false, "name": "resolve_any_xref of MathDomain", "ret_type": {".class": "Instance", "args": [{".class": "TupleType", "implicit": false, "items": ["builtins.str", {".class": "AnyType", "missing_import_name": "sphinx.domains.math.Element", "source_any": null, "type_of_any": 3}], "partial_fallback": {".class": "Instance", "args": [{".class": "AnyType", "missing_import_name": null, "source_any": null, "type_of_any": 6}], "type_ref": "builtins.tuple"}}], "type_ref": "builtins.list"}, "type_guard": null, "unpack_kwargs": false, "variables": []}}}, "resolve_xref": {".class": "SymbolTableNode", "kind": "Mdef", "node": {".class": "FuncDef", "abstract_status": 0, "arg_kinds": [0, 0, 0, 0, 0, 0, 0, 0], "arg_names": ["self", "env", "fromdocname", "builder", "typ", "target", "node", "contnode"], "dataclass_transform_spec": null, "flags": [], "fullname": "sphinx.domains.math.MathDomain.resolve_xref", "name": "resolve_xref", "type": {".class": "CallableType", "arg_kinds": [0, 0, 0, 0, 0, 0, 0, 0], "arg_names": ["self", "env", "fromdocname", "builder", "typ", "target", "node", "contnode"], "arg_types": ["sphinx.domains.math.MathDomain", "sphinx.environment.BuildEnvironment", "builtins.str", "sphinx.builders.Builder", "builtins.str", "builtins.str", "sphinx.addnodes.pending_xref", {".class": "AnyType", "missing_import_name": "sphinx.domains.math.Element", "source_any": null, "type_of_any": 3}], "bound_args": [], "def_extras": {"first_arg": "self"}, "fallback": "builtins.function", "from_concatenate": false, "implicit": false, "is_ellipsis_args": false, "name": "resolve_xref of MathDomain", "ret_type": {".class": "UnionType", "items": [{".class": "AnyType", "missing_import_name": "sphinx.domains.math.Element", "source_any": null, "type_of_any": 3}, {".class": "NoneType"}]}, "type_guard": null, "unpack_kwargs": false, "variables": []}}}, "roles": {".class": "SymbolTableNode", "kind": "Mdef", "node": {".class": "Var", "flags": ["is_initialized_in_class", "is_inferred", "has_explicit_value"], "fullname": "sphinx.domains.math.MathDomain.roles", "name": "roles", "type": {".class": "Instance", "args": ["builtins.str", {".class": "UnionType", "items": [{".class": "TypeAliasType", "args": [], "type_ref": "sphinx.util.typing.RoleFunction"}, "sphinx.roles.XRefRole"]}], "type_ref": "builtins.dict"}}}}, "self_type": null, "slots": null, "tuple_type": null, "type_vars": [], "typeddict_type": null}}, "MathReferenceRole": {".class": "SymbolTableNode", "kind": "Gdef", "node": {".class": "TypeInfo", "_promote": [], "abstract_attributes": [], "alt_promote": null, "bases": ["sphinx.roles.XRefRole"], "dataclass_transform_spec": null, "declared_metaclass": null, "defn": {".class": "ClassDef", "fullname": "sphinx.domains.math.MathReferenceRole", "name": "MathReferenceRole", "type_vars": []}, "deletable_attributes": [], "flags": [], "fullname": "sphinx.domains.math.MathReferenceRole", "has_param_spec_type": false, "metaclass_type": null, "metadata": {}, "module_name": "sphinx.domains.math", "mro": ["sphinx.domains.math.MathReferenceRole", "sphinx.roles.XRefRole", "sphinx.util.docutils.ReferenceRole", "sphinx.util.docutils.SphinxRole", "builtins.object"], "names": {".class": "SymbolTable", "result_nodes": {".class": "SymbolTableNode", "kind": "Mdef", "node": {".class": "FuncDef", "abstract_status": 0, "arg_kinds": [0, 0, 0, 0, 0], "arg_names": ["self", "document", "env", "node", "is_ref"], "dataclass_transform_spec": null, "flags": [], "fullname": "sphinx.domains.math.MathReferenceRole.result_nodes", "name": "result_nodes", "type": {".class": "CallableType", "arg_kinds": [0, 0, 0, 0, 0], "arg_names": ["self", "document", "env", "node", "is_ref"], "arg_types": ["sphinx.domains.math.MathReferenceRole", {".class": "AnyType", "missing_import_name": "sphinx.domains.math.nodes", "source_any": null, "type_of_any": 3}, "sphinx.environment.BuildEnvironment", {".class": "AnyType", "missing_import_name": "sphinx.domains.math.Element", "source_any": null, "type_of_any": 3}, "builtins.bool"], "bound_args": [], "def_extras": {"first_arg": "self"}, "fallback": "builtins.function", "from_concatenate": false, "implicit": false, "is_ellipsis_args": false, "name": "result_nodes of MathReferenceRole", "ret_type": {".class": "TupleType", "implicit": false, "items": [{".class": "Instance", "args": [{".class": "AnyType", "missing_import_name": "sphinx.domains.math.Node", "source_any": null, "type_of_any": 3}], "type_ref": "builtins.list"}, {".class": "Instance", "args": [{".class": "AnyType", "missing_import_name": "sphinx.domains.math.system_message", "source_any": null, "type_of_any": 3}], "type_ref": "builtins.list"}], "partial_fallback": {".class": "Instance", "args": [{".class": "AnyType", "missing_import_name": null, "source_any": null, "type_of_any": 6}], "type_ref": "builtins.tuple"}}, "type_guard": null, "unpack_kwargs": false, "variables": []}}}}, "self_type": null, "slots": null, "tuple_type": null, "type_vars": [], "typeddict_type": null}}, "Node": {".class": "SymbolTableNode", "kind": "Gdef", "node": {".class": "Var", "flags": ["is_suppressed_import", "is_ready", "is_inferred"], "fullname": "sphinx.domains.math.Node", "name": "Node", "type": {".class": "AnyType", "missing_import_name": "sphinx.domains.math.Node", "source_any": null, "type_of_any": 3}}}, "Optional": {".class": "SymbolTableNode", "cross_ref": "typing.Optional", "kind": "Gdef"}, "Sphinx": {".class": "SymbolTableNode", "cross_ref": "sphinx.application.Sphinx", "kind": "Gdef"}, "TYPE_CHECKING": {".class": "SymbolTableNode", "cross_ref": "typing.TYPE_CHECKING", "kind": "Gdef"}, "Tuple": {".class": "SymbolTableNode", "cross_ref": "typing.Tuple", "kind": "Gdef"}, "XRefRole": {".class": "SymbolTableNode", "cross_ref": "sphinx.roles.XRefRole", "kind": "Gdef"}, "__": {".class": "SymbolTableNode", "cross_ref": "sphinx.locale.__", "kind": "Gdef"}, "__annotations__": {".class": "SymbolTableNode", "kind": "Gdef", "node": {".class": "Var", "flags": ["is_ready"], "fullname": "sphinx.domains.math.__annotations__", "name": "__annotations__", "type": {".class": "Instance", "args": ["builtins.str", {".class": "AnyType", "missing_import_name": null, "source_any": null, "type_of_any": 6}], "type_ref": "builtins.dict"}}}, "__doc__": {".class": "SymbolTableNode", "kind": "Gdef", "node": {".class": "Var", "flags": ["is_ready"], "fullname": "sphinx.domains.math.__doc__", "name": "__doc__", "type": "builtins.str"}}, "__file__": {".class": "SymbolTableNode", "kind": "Gdef", "node": {".class": "Var", "flags": ["is_ready"], "fullname": "sphinx.domains.math.__file__", "name": "__file__", "type": "builtins.str"}}, "__name__": {".class": "SymbolTableNode", "kind": "Gdef", "node": {".class": "Var", "flags": ["is_ready"], "fullname": "sphinx.domains.math.__name__", "name": "__name__", "type": "builtins.str"}}, "__package__": {".class": "SymbolTableNode", "kind": "Gdef", "node": {".class": "Var", "flags": ["is_ready"], "fullname": "sphinx.domains.math.__package__", "name": "__package__", "type": "builtins.str"}}, "logger": {".class": "SymbolTableNode", "kind": "Gdef", "node": {".class": "Var", "flags": ["is_inferred", "has_explicit_value"], "fullname": "sphinx.domains.math.logger", "name": "logger", "type": "sphinx.util.logging.SphinxLoggerAdapter"}}, "logging": {".class": "SymbolTableNode", "cross_ref": "sphinx.util.logging", "kind": "Gdef"}, "make_id": {".class": "SymbolTableNode", "kind": "Gdef", "node": {".class": "Var", "flags": ["is_suppressed_import", "is_ready", "is_inferred"], "fullname": "sphinx.domains.math.make_id", "name": "make_id", "type": {".class": "AnyType", "missing_import_name": "sphinx.domains.math.make_id", "source_any": null, "type_of_any": 3}}}, "make_refnode": {".class": "SymbolTableNode", "cross_ref": "sphinx.util.nodes.make_refnode", "kind": "Gdef"}, "nodes": {".class": "SymbolTableNode", "kind": "Gdef", "node": {".class": "Var", "flags": ["is_suppressed_import", "is_ready", "is_inferred"], "fullname": "sphinx.domains.math.nodes", "name": "nodes", "type": {".class": "AnyType", "missing_import_name": "sphinx.domains.math.nodes", "source_any": null, "type_of_any": 3}}}, "pending_xref": {".class": "SymbolTableNode", "cross_ref": "sphinx.addnodes.pending_xref", "kind": "Gdef"}, "setup": {".class": "SymbolTableNode", "kind": "Gdef", "node": {".class": "FuncDef", "abstract_status": 0, "arg_kinds": [0], "arg_names": ["app"], "dataclass_transform_spec": null, "flags": [], "fullname": "sphinx.domains.math.setup", "name": "setup", "type": {".class": "CallableType", "arg_kinds": [0], "arg_names": ["app"], "arg_types": ["sphinx.application.Sphinx"], "bound_args": [], "def_extras": {"first_arg": null}, "fallback": "builtins.function", "from_concatenate": false, "implicit": false, "is_ellipsis_args": false, "name": "setup", "ret_type": {".class": "Instance", "args": ["builtins.str", {".class": "AnyType", "missing_import_name": null, "source_any": null, "type_of_any": 2}], "type_ref": "builtins.dict"}, "type_guard": null, "unpack_kwargs": false, "variables": []}}}, "system_message": {".class": "SymbolTableNode", "kind": "Gdef", "node": {".class": "Var", "flags": ["is_suppressed_import", "is_ready", "is_inferred"], "fullname": "sphinx.domains.math.system_message", "name": "system_message", "type": {".class": "AnyType", "missing_import_name": "sphinx.domains.math.system_message", "source_any": null, "type_of_any": 3}}}}, "path": "/home/anton/micromamba/envs/py310/lib/python3.10/site-packages/sphinx/domains/math.py"}